LICENSE
MANIFEST.in
README.md
setup.cfg
setup.py
django_grafana.egg-info/PKG-INFO
django_grafana.egg-info/SOURCES.txt
django_grafana.egg-info/dependency_links.txt
django_grafana.egg-info/entry_points.txt
django_grafana.egg-info/requires.txt
django_grafana.egg-info/top_level.txt
grafana/__init__.py
grafana/admin.py
grafana/client.py
grafana/models.py
grafana/urls.py
grafana/views.py
grafana/mutators/__init__.py
grafana/mutators/null.py
grafana/mutators/refresh.py
grafana/templates/grafana/annotation_list.html
grafana/templates/grafana/dashboard_detail.html
grafana/templates/grafana/dashboard_mutate.html
grafana/templates/grafana/organization_detail.html
grafana/templates/grafana/organization_list.html
grafana/templates/grafana/organization_members.html
grafana/templates/grafana/version_detail.html
grafana/templates/grafana/version_list.html
grafana/templatetags/__init__.py
grafana/templatetags/grafana.py